extensort/__init__.py
extensort/extensort.py
extensort-0.1.1.dist-info/METADATA
extensort-0.1.1.dist-info/WHEEL
extensort-0.1.1.dist-info/licenses/LICENSE
extensort-0.1.1.dist-info/RECORD
