Metadata-Version: 2.3
Name: extensort
Version: 0.1.1
Summary: A module for sorting files into folders based on their extensions
Project-URL: Homepage, https://github.com/SMFRafin/extensort
Project-URL: Bug Tracker, https://github.com/SMFRafin/extensort/issues
Author-email: SMF <muntasinfayaz@gmail.com>
Classifier: License :: OSI Approved :: MIT License
Classifier: Operating System :: OS Independent
Classifier: Programming Language :: Python :: 3
Requires-Python: >=3.7
Requires-Dist: colorama
